mspgsql-1.0.0.dev1.dist-info/DESCRIPTION.rst
mspgsql-1.0.0.dev1.dist-info/METADATA
mspgsql-1.0.0.dev1.dist-info/RECORD
mspgsql-1.0.0.dev1.dist-info/WHEEL
mspgsql-1.0.0.dev1.dist-info/metadata.json
mspgsql-1.0.0.dev1.dist-info/top_level.txt
musicstory/pgsql/__init__.py
