Metadata-Version: 2.0
Name: mspgsql
Version: 1.0.0.dev1
Summary: Python PostgreSQL library for Music-Story dataflows
Home-page: UNKNOWN
Author: Music-Story
Author-email: webmaster@music-story.com
License: UNKNOWN
Platform: UNKNOWN
Requires-Dist: python-dotenv (<0.8,>=0.7.1)
Requires-Dist: psycopg2 (<3.0,>=2.7.0)
